cypresspoint/__init__.py
cypresspoint/checkpoint.py
cypresspoint/compat.py
cypresspoint/datatype.py
cypresspoint/log.py
cypresspoint/modinput.py
cypresspoint/monkeypatch.py
cypresspoint/rest_handler.py
cypresspoint/results.py
cypresspoint/searchcommand.py
cypresspoint/spath.py
cypresspoint-0.8.3.dist-info/AUTHORS.rst
cypresspoint-0.8.3.dist-info/LICENSE
cypresspoint-0.8.3.dist-info/METADATA
cypresspoint-0.8.3.dist-info/WHEEL
cypresspoint-0.8.3.dist-info/top_level.txt
cypresspoint-0.8.3.dist-info/RECORD
