Metadata-Version: 2.1
Name: cypresspoint
Version: 0.8.3
Summary: Python helper bits for Splunk add-on development
Home-page: https://github.com/Kintyre/cypresspoint
Author: Lowell Alleman
Author-email: lowell.alleman@cdillc.com
License: Apache Software License 2.0
Keywords: cypresspoint
Classifier: Development Status :: 2 - Pre-Alpha
Classifier: Intended Audience :: Developers
Classifier: License :: OSI Approved :: Apache Software License
Classifier: Natural Language :: English
Classifier: Programming Language :: Python :: 3
Classifier: Programming Language :: Python :: 3.7
Classifier: Programming Language :: Python :: 3.8
Classifier: Programming Language :: Python :: 3.9
Classifier: Programming Language :: Python :: 3.10
Classifier: Programming Language :: Python :: 3.11
Requires-Python: >=3.7
License-File: LICENSE
License-File: AUTHORS.rst
Requires-Dist: splunk-sdk (>=1.7)
